taypi_create-1.0.0.dist-info/licenses/LICENSE
taypiproject/__init__.py
taypiproject/cli.py
taypiproject/docker_modified.py
taypiproject/entity_generator.py
taypiproject/envdocker.py
taypiproject/git_generator.py
taypiproject/main_modified.py
taypiproject/microservice_generator.py
taypiproject/migration_generator.py
taypiproject/project_generator.py
taypiproject/readme_modified.py
taypiproject/site_generator.py
taypiproject/templates/dockerfile.txt
taypiproject/templates/env.txt
taypiproject/templates/requirements.txt
taypiproject/templates/entity/entity.txt
taypiproject/templates/entity/input_dto.txt
taypiproject/templates/entity/insert_validation.txt
taypiproject/templates/entity/model.txt
taypiproject/templates/entity/output_dto.txt
taypiproject/templates/entity/repository.txt
taypiproject/templates/entity/repository_impl.txt
taypiproject/templates/entity/router.txt
taypiproject/templates/entity/service.txt
taypiproject/templates/entity/update_validation.txt
taypiproject/templates/entity/use_case_create.txt
taypiproject/templates/entity/use_case_delete.txt
taypiproject/templates/entity/use_case_get_all.txt
taypiproject/templates/entity/use_case_get_by_id.txt
taypiproject/templates/entity/use_case_update.txt
taypiproject/templates/entity/value_object_datetime.txt
taypiproject/templates/microservice/alembic.ini.txt
taypiproject/templates/microservice/alembic_env.txt
taypiproject/templates/microservice/alembic_script.txt
taypiproject/templates/microservice/command.txt
taypiproject/templates/microservice/command_seeder.txt
taypiproject/templates/microservice/connections.txt
taypiproject/templates/microservice/database_settings.txt
taypiproject/templates/microservice/domain_filter.txt
taypiproject/templates/microservice/handler.txt
taypiproject/templates/microservice/input_filter.txt
taypiproject/templates/microservice/main.txt
taypiproject/templates/microservice/messages.txt
taypiproject/templates/microservice/readme.txt
taypiproject/templates/microservice/secret.txt
taypi_create-1.0.0.dist-info/METADATA
taypi_create-1.0.0.dist-info/WHEEL
taypi_create-1.0.0.dist-info/entry_points.txt
taypi_create-1.0.0.dist-info/top_level.txt
taypi_create-1.0.0.dist-info/RECORD
