Metadata-Version: 2.4
Name: taypi-create
Version: 1.0.0
Summary: FastAPI and PostGreSQL.
Author: Juan David Corrales Saldarriaga
Author-email: sistemas@taypi.com
License: Proprietary
Classifier: Programming Language :: Python :: 3
Classifier: License :: Other/Proprietary License
Classifier: Operating System :: OS Independent
Requires-Python: >=3.8
License-File: LICENSE
Requires-Dist: inflection
Requires-Dist: ruamel.yaml
Requires-Dist: Jinja2
Dynamic: author
Dynamic: author-email
Dynamic: classifier
Dynamic: description
Dynamic: description-content-type
Dynamic: license
Dynamic: license-file
Dynamic: requires-dist
Dynamic: requires-python
Dynamic: summary
